{
  "key": "port_n500_d10_g0.12",
  "n": 500,
  "split": 0.5,
  "d": 10,
  "gamma": 0.12,
  "dgp": "gaussian",
  "reps": 500,
  "elapsed_s": 3.3691282272338867,
  "summaries": {
    "NV": {
      "method": "NV",
      "n_reps": 496,
      "target": 0.95,
      "coverage": 0.5745967741935484,
      "coverage_lo": 0.530677182421851,
      "coverage_hi": 0.6173697606520441,
      "coverage_gap": -0.3754032258064516,
      "meets_target": false,
      "significantly_below": true,
      "mean_obj": -0.11719769142840374,
      "obj_se": 0.0001923454539554457,
      "mean_oracle_gap": null,
      "oracle_gap_se": null,
      "mean_rel_oracle_gap": null,
      "mean_excess_s": null,
      "selected_s_std": null,
      "failure_rate": 0.0,
      "mean_return": 0.11719769142840374,
      "mean_true_cvar": 0.12017711331922594
    },
    "UG": {
      "method": "UG",
      "n_reps": 496,
      "target": 0.95,
      "coverage": 0.9254032258064516,
      "coverage_lo": 0.8988696095779661,
      "coverage_hi": 0.9453980928164089,
      "coverage_gap": -0.024596774193548332,
      "meets_target": false,
      "significantly_below": true,
      "mean_obj": -0.11365060253664078,
      "obj_se": 0.00014240678218391468,
      "mean_oracle_gap": null,
      "oracle_gap_se": null,
      "mean_rel_oracle_gap": null,
      "mean_excess_s": null,
      "selected_s_std": null,
      "failure_rate": 0.0,
      "mean_return": 0.11365060253664078,
      "mean_true_cvar": 0.10959760682068366
    },
    "NGS": {
      "method": "NGS",
      "n_reps": 496,
      "target": 0.95,
      "coverage": 0.9536290322580645,
      "coverage_lo": 0.9313809079729714,
      "coverage_hi": 0.9689045566655801,
      "coverage_gap": 0.003629032258064546,
      "meets_target": true,
      "significantly_below": false,
      "mean_obj": -0.11339310369027096,
      "obj_se": 0.0001353492089157796,
      "mean_oracle_gap": null,
      "oracle_gap_se": null,
      "mean_rel_oracle_gap": null,
      "mean_excess_s": null,
      "selected_s_std": null,
      "failure_rate": 0.0,
      "mean_return": 0.11339310369027096,
      "mean_true_cvar": 0.10890843640427003
    },
    "UNGS": {
      "method": "UNGS",
      "n_reps": 496,
      "target": 0.95,
      "coverage": 0.9637096774193549,
      "coverage_lo": 0.9433684502572192,
      "coverage_hi": 0.9769233580399669,
      "coverage_gap": 0.013709677419354915,
      "meets_target": true,
      "significantly_below": false,
      "mean_obj": -0.11329489632433072,
      "obj_se": 0.00013171843409212435,
      "mean_oracle_gap": null,
      "oracle_gap_se": null,
      "mean_rel_oracle_gap": null,
      "mean_excess_s": null,
      "selected_s_std": null,
      "failure_rate": 0.0,
      "mean_return": 0.11329489632433072,
      "mean_true_cvar": 0.10866523116967212
    },
    "benchmark": {
      "method": "benchmark",
      "n_reps": 496,
      "target": 0.95,
      "coverage": 0.0846774193548387,
      "coverage_lo": 0.0632551338479326,
      "coverage_hi": 0.11248350741632693,
      "coverage_gap": -0.8653225806451612,
      "meets_target": false,
      "significantly_below": true,
      "mean_obj": -0.12298089126248785,
      "obj_se": 0.0002082175989611404,
      "mean_oracle_gap": null,
      "oracle_gap_se": null,
      "mean_rel_oracle_gap": null,
      "mean_excess_s": null,
      "selected_s_std": null,
      "failure_rate": 0.0,
      "mean_return": 0.12298089126248785,
      "mean_true_cvar": 0.14234273985100798
    },
    "_n_replication_errors": 4
  },
  "_provenance": {
    "git_commit": "d34ff2286f94f415327062e8df3721cd49ec3996",
    "git_dirty": true,
    "versions": {
      "numpy": "2.5.1",
      "scipy": "1.18.0",
      "cvxpy": "1.9.2",
      "gurobipy": "13.0.2"
    },
    "timestamp": null
  }
}